<?xml version="1.0"?>
<!-- <!DOCTYPE Chapters SYSTEM "matroskachapters.dtd"> -->
<Chapters>
  <EditionEntry>
    <EditionFlagHidden>0</EditionFlagHidden>
    <EditionFlagDefault>0</EditionFlagDefault>
    <EditionUID>2693924790</EditionUID>
    <ChapterAtom>
      <ChapterUID>1090963120</ChapterUID>
      <ChapterTimeStart>00:00:00.000000000</ChapterTimeStart>
      <ChapterFlagHidden>0</ChapterFlagHidden>
      <ChapterFlagEnabled>1</ChapterFlagEnabled>
      <ChapterDisplay>
        <ChapterString>Opening</ChapterString>
        <ChapterLanguage>eng</ChapterLanguage>
      </ChapterDisplay>
    </ChapterAtom>
    <ChapterAtom>
      <ChapterUID>2372663221</ChapterUID>
      <ChapterTimeStart>00:01:43.437000000</ChapterTimeStart>
      <ChapterFlagHidden>0</ChapterFlagHidden>
      <ChapterFlagEnabled>1</ChapterFlagEnabled>
      <ChapterDisplay>
        <ChapterString>Part A</ChapterString>
        <ChapterLanguage>eng</ChapterLanguage>
      </ChapterDisplay>
    </ChapterAtom>
    <ChapterAtom>
      <ChapterUID>1155648917</ChapterUID>
      <ChapterTimeStart>00:12:12.023000000</ChapterTimeStart>
      <ChapterFlagHidden>0</ChapterFlagHidden>
      <ChapterFlagEnabled>1</ChapterFlagEnabled>
      <ChapterDisplay>
        <ChapterString>Part B</ChapterString>
        <ChapterLanguage>eng</ChapterLanguage>
      </ChapterDisplay>
    </ChapterAtom>
    <ChapterAtom>
      <ChapterUID>2941683338</ChapterUID>
      <ChapterTimeStart>00:21:44.053000000</ChapterTimeStart>
      <ChapterFlagHidden>0</ChapterFlagHidden>
      <ChapterFlagEnabled>1</ChapterFlagEnabled>
      <ChapterDisplay>
        <ChapterString>Ending</ChapterString>
        <ChapterLanguage>eng</ChapterLanguage>
      </ChapterDisplay>
    </ChapterAtom>
  </EditionEntry>
</Chapters>
